alpaca_backtrader_api/__init__.py
alpaca_backtrader_api/alpacabroker.py
alpaca_backtrader_api/alpacadata.py
alpaca_backtrader_api/alpacastore.py
alpaca_backtrader_api-0.15.0.dist-info/LICENSE
alpaca_backtrader_api-0.15.0.dist-info/METADATA
alpaca_backtrader_api-0.15.0.dist-info/WHEEL
alpaca_backtrader_api-0.15.0.dist-info/top_level.txt
alpaca_backtrader_api-0.15.0.dist-info/RECORD
