Metadata-Version: 2.1
Name: alpaca-backtrader-api
Version: 0.15.0
Summary: Alpaca API within backtrader
Home-page: https://github.com/alpacahq/alpaca-backtrader-api
Author: Alpaca
Author-email: oss@alpaca.markets
License: UNKNOWN
Keywords: financial,timeseries,api,trade,backtrader
Platform: UNKNOWN
Classifier: Programming Language :: Python :: 3
Classifier: Programming Language :: Python :: 3.7
Classifier: Programming Language :: Python :: 3.8
Classifier: Programming Language :: Python :: 3.9
Classifier: Operating System :: OS Independent
Requires-Dist: backtrader (==1.9.76.123)
Requires-Dist: alpaca-trade-api (==1.4.3)
Requires-Dist: exchange-calendars (==3.4)
Requires-Dist: matplotlib (==2.2.5)
Requires-Dist: msgpack (==1.0.2)
Requires-Dist: numpy (==1.21.2)
Requires-Dist: pandas (==1.3.2)
